{
  "info": {
    "_postman_id": "4b5d63f2-1b1e-450a-9d90-7d722d3b2f56",
    "name": "Project Management Platform",
    "description": "API collection for the SaaS Project Management Platform.",
    "schema": "https://schema.getpostman.com/json/collection/v2.1.0/collection.json"
  },
  "item": [
    {
      "name": "Auth",
      "item": [
        {
          "name": "Login",
          "event": [
            {
              "listen": "test",
              "script": {
                "exec": [
                  "const response = pm.response.json();",
                  "if (response.success && response.data) {",
                  "    pm.environment.set(\"access_token\", response.data.accessToken);",
                  "    pm.environment.set(\"refresh_token\", response.data.refreshToken);",
                  "}"
                ],
                "type": "text/javascript"
              }
            }
          ],
          "request": {
            "method": "POST",
            "header": [],
            "body": {
              "mode": "raw",
              "raw": "{\n  \"email\": \"admin@platform.com\",\n  \"password\": \"AdminPassword123!\"\n}",
              "options": {
                "raw": {
                  "language": "json"
                }
              }
            },
            "url": {
              "raw": "{{base_url}}/auth/login",
              "host": [
                "{{base_url}}"
              ],
              "path": [
                "auth",
                "login"
              ]
            }
          },
          "response": []
        },
        {
          "name": "Logout",
          "event": [
            {
              "listen": "test",
              "script": {
                "exec": [
                  "if (pm.response.code === 200) {",
                  "    pm.environment.unset(\"access_token\");",
                  "    pm.environment.unset(\"refresh_token\");",
                  "}"
                ],
                "type": "text/javascript"
              }
            }
          ],
          "request": {
            "method": "POST",
            "header": [
              {
                "key": "Authorization",
                "value": "Bearer {{access_token}}",
                "type": "text"
              }
            ],
            "url": {
              "raw": "{{base_url}}/auth/logout",
              "host": [
                "{{base_url}}"
              ],
              "path": [
                "auth",
                "logout"
              ]
            }
          },
          "response": []
        },
        {
          "name": "Refresh Token",
          "event": [
            {
              "listen": "test",
              "script": {
                "exec": [
                  "const response = pm.response.json();",
                  "if (response.success && response.data) {",
                  "    pm.environment.set(\"access_token\", response.data.accessToken);",
                  "    pm.environment.set(\"refresh_token\", response.data.refreshToken);",
                  "}"
                ],
                "type": "text/javascript"
              }
            }
          ],
          "request": {
            "method": "POST",
            "header": [],
            "body": {
              "mode": "raw",
              "raw": "{\n  \"refreshToken\": \"{{refresh_token}}\"\n}",
              "options": {
                "raw": {
                  "language": "json"
                }
              }
            },
            "url": {
              "raw": "{{base_url}}/auth/refresh",
              "host": [
                "{{base_url}}"
              ],
              "path": [
                "auth",
                "refresh"
              ]
            }
          },
          "response": []
        },
        {
          "name": "Change Password",
          "request": {
            "method": "POST",
            "header": [
              {
                "key": "Authorization",
                "value": "Bearer {{access_token}}",
                "type": "text"
              }
            ],
            "body": {
              "mode": "raw",
              "raw": "{\n  \"oldPassword\": \"AdminPassword123!\",\n  \"newPassword\": \"NewAdminPassword123!\"\n}",
              "options": {
                "raw": {
                  "language": "json"
                }
              }
            },
            "url": {
              "raw": "{{base_url}}/auth/changepassword",
              "host": [
                "{{base_url}}"
              ],
              "path": [
                "auth",
                "changepassword"
              ]
            }
          },
          "response": []
        },
        {
          "name": "Get Profile (Me)",
          "request": {
            "method": "GET",
            "header": [
              {
                "key": "Authorization",
                "value": "Bearer {{access_token}}",
                "type": "text"
              }
            ],
            "url": {
              "raw": "{{base_url}}/auth/me",
              "host": [
                "{{base_url}}"
              ],
              "path": [
                "auth",
                "me"
              ]
            }
          },
          "response": []
        }
      ]
    }
  ]
}
